linguistica/VERSION
linguistica/__init__.py
linguistica/__main__.py
linguistica/cli.py
linguistica/lexicon.py
linguistica/manifold.py
linguistica/ngram.py
linguistica/phon.py
linguistica/release.py
linguistica/signature.py
linguistica/trie.py
linguistica/util.py
linguistica/datasets/__init__.py
linguistica/datasets/english-brown.txt
linguistica/datasets/english-cmudict.dx1
linguistica/gui/__init__.py
linguistica/gui/d3.min.js
linguistica/gui/lxa_splash_screen.png
linguistica/gui/main_window.py
linguistica/gui/util.py
linguistica/gui/worker.py
linguistica/tests/__init__.py
linguistica/tests/test_manifold.py
linguistica/tests/test_ngram.py
linguistica/tests/test_phon.py
linguistica/tests/test_read.py
linguistica/tests/test_signature.py
linguistica/tests/test_trie.py
linguistica/tests/test_util.py
linguistica/tests/data/affixes_to_signatures.txt
linguistica/tests/data/broken_words_left_to_right.txt
linguistica/tests/data/broken_words_right_to_left.txt
linguistica/tests/data/contexts_to_words.txt
linguistica/tests/data/phone_bigram_counter.txt
linguistica/tests/data/phone_trigram_counter.txt
linguistica/tests/data/phone_unigram_counter.txt
linguistica/tests/data/predecessors.txt
linguistica/tests/data/signatures_to_stems.txt
linguistica/tests/data/signatures_to_words.txt
linguistica/tests/data/stems_to_signatures.txt
linguistica/tests/data/stems_to_words.txt
linguistica/tests/data/successors.txt
linguistica/tests/data/word_bigram_counter.txt
linguistica/tests/data/word_trigram_counter.txt
linguistica/tests/data/word_unigram_counter.txt
linguistica/tests/data/wordlist.txt
linguistica/tests/data/words_to_contexts.txt
linguistica/tests/data/words_to_neighbors.txt
linguistica/tests/data/words_to_signatures.txt
linguistica/tests/data/words_to_sigtransforms.txt
linguistica-5.2.1.dist-info/LICENSE.txt
linguistica-5.2.1.dist-info/METADATA
linguistica-5.2.1.dist-info/WHEEL
linguistica-5.2.1.dist-info/entry_points.txt
linguistica-5.2.1.dist-info/top_level.txt
linguistica-5.2.1.dist-info/RECORD
