Metadata-Version: 2.1
Name: linguistica
Version: 5.2.1
Summary: Linguistica 5: Unsupervised Learning of Linguistic Structure
Home-page: http://linguistica.uchicago.edu/
Author: Jackson Lee
Author-email: jacksonlunlee@gmail.com
License: MIT License
Keywords: computational linguistics,natural language processing,NLP,linguistics,corpora,speech,language,machine learning,unsupervised learning,data visualization
Platform: UNKNOWN
Classifier: Development Status :: 4 - Beta
Classifier: Intended Audience :: Developers
Classifier: Intended Audience :: Education
Classifier: Intended Audience :: Information Technology
Classifier: Intended Audience :: Science/Research
Classifier: License :: OSI Approved :: MIT License
Classifier: Operating System :: OS Independent
Classifier: Programming Language :: Python :: 2
Classifier: Programming Language :: Python :: 2.7
Classifier: Programming Language :: Python :: 3
Classifier: Programming Language :: Python :: 3.4
Classifier: Programming Language :: Python :: 3.5
Classifier: Programming Language :: Python :: 3.6
Classifier: Programming Language :: Python :: 3.7
Classifier: Topic :: Scientific/Engineering
Classifier: Topic :: Scientific/Engineering :: Artificial Intelligence
Classifier: Topic :: Scientific/Engineering :: Human Machine Interfaces
Classifier: Topic :: Scientific/Engineering :: Information Analysis
Classifier: Topic :: Text Processing
Classifier: Topic :: Text Processing :: Filters
Classifier: Topic :: Text Processing :: General
Classifier: Topic :: Text Processing :: Indexing
Classifier: Topic :: Text Processing :: Linguistic
Requires-Dist: six (>=1.10.0)
Requires-Dist: numpy (>=1.12.1)
Requires-Dist: scipy (>=0.19.0)
Requires-Dist: networkx (>=1.11)
